.appveyor.yml
.bumpversion.cfg
.cookiecutterrc
.coveragerc
.editorconfig
.pre-commit-config.yaml
.readthedocs.yml
.travis.yml
AUTHORS.rst
CHANGELOG.rst
CONTRIBUTING.rst
LICENSE
MANIFEST.in
README.rst
setup.cfg
setup.py
tox.ini
ci/appveyor-with-compiler.cmd
ci/bootstrap.py
ci/requirements.txt
ci/templates/.appveyor.yml
ci/templates/.travis.yml
docs/authors.rst
docs/changelog.rst
docs/conf.py
docs/contributing.rst
docs/index.rst
docs/installation.rst
docs/readme.rst
docs/requirements.txt
docs/spelling_wordlist.txt
docs/usage.rst
docs/reference/index.rst
docs/reference/ppdownloader.rst
src/ppDownloader.egg-info/PKG-INFO
src/ppDownloader.egg-info/SOURCES.txt
src/ppDownloader.egg-info/dependency_links.txt
src/ppDownloader.egg-info/entry_points.txt
src/ppDownloader.egg-info/not-zip-safe
src/ppDownloader.egg-info/top_level.txt
src/ppdownloader/__init__.py
src/ppdownloader/__main__.py
src/ppdownloader/cli.py
tests/test_ppdownloader.py