Metadata-Version: 1.2
Name: ppDownloader
Version: 0.0.1
Summary: A python download accelerator that uses parallel requests to increase download speed.
Home-page: https://github.com/AriaBagheri/ppDownloader
Author: Aria Bagheri
Author-email: ariab9342@gmail.com
License: MIT
Project-URL: Documentation, https://ppDownloader.readthedocs.io/
Project-URL: Changelog, https://ppDownloader.readthedocs.io/en/latest/changelog.html
Project-URL: Issue Tracker, https://github.com/AriaBagheri/ppDownloader/issues
Keywords: parallel downloader,python downloader,fast downloader
Platform: UNKNOWN
Classifier: Development Status :: 5 - Production/Stable
Classifier: Intended Audience :: Developers
Classifier: License :: OSI Approved :: MIT License
Classifier: Operating System :: Unix
Classifier: Operating System :: POSIX
Classifier: Operating System :: Microsoft :: Windows
Classifier: Programming Language :: Python
Classifier: Programming Language :: Python :: 3
Classifier: Programming Language :: Python :: 3.7
Classifier: Programming Language :: Python :: 3.8
Classifier: Topic :: Utilities
Requires-Python: !=3.0.*, !=3.1.*, !=3.2.*, !=3.3.*, !=3.4.*
